LICENSE
MANIFEST.in
README.rst
requirements-dev.txt
requirements-test.txt
requirements.txt
setup.cfg
setup.py
tox.ini
docs/Makefile
docs/source/conf.py
docs/source/index.rst
docs/source/linebot.models.rst
docs/source/linebot.rst
gg11.egg-info/PKG-INFO
gg11.egg-info/SOURCES.txt
gg11.egg-info/dependency_links.txt
gg11.egg-info/requires.txt
gg11.egg-info/top_level.txt
linebt/__about__.py
linebt/__init__.py
linebt/api.py
linebt/exceptions.py
linebt/http_client.py
linebt/utils.py
linebt/webhook.py
linebt/models/__init__.py
linebt/models/base.py
linebt/models/error.py
linebt/models/events.py
linebt/models/imagemap.py
linebt/models/messages.py
linebt/models/responses.py
linebt/models/send_messages.py
linebt/models/sources.py
linebt/models/template.py
tests/__init__.py
tests/test_utils.py
tests/test_webhook.py
tests/api/__init__.py
tests/api/test_error_handle.py
tests/api/test_get_content.py
tests/api/test_get_member_ids.py
tests/api/test_get_member_profile.py
tests/api/test_get_profile.py
tests/api/test_leave.py
tests/api/test_send_audio_message.py
tests/api/test_send_image_message.py
tests/api/test_send_imagemap_message.py
tests/api/test_send_location_message.py
tests/api/test_send_sticker_message.py
tests/api/test_send_template_message.py
tests/api/test_send_text_message.py
tests/api/test_send_video_message.py
tests/models/__init__.py
tests/models/test_base.py
tests/text/webhook.json